web/__init__.py
web/web.py
Eebuilder-1.0.0.1.dist-info/METADATA
Eebuilder-1.0.0.1.dist-info/WHEEL
Eebuilder-1.0.0.1.dist-info/top_level.txt
Eebuilder-1.0.0.1.dist-info/RECORD
