Metadata-Version: 2.1
Name: Eebuilder
Version: 1.0.0.1
Summary: A Python package for creating HTML files
Home-page: https://github.com/SuperMeteorite/Eebuilder
Author: Will F
Author-email: forsbergw82@gmail.com
License: UNKNOWN
Platform: UNKNOWN
Classifier: Programming Language :: Python :: 3
